multiproject/__init__.py
multiproject/extension.py
multiproject/utils.py
sphinx_multiproject-1.0.0.dist-info/LICENSE
sphinx_multiproject-1.0.0.dist-info/METADATA
sphinx_multiproject-1.0.0.dist-info/WHEEL
sphinx_multiproject-1.0.0.dist-info/top_level.txt
sphinx_multiproject-1.0.0.dist-info/RECORD
