Metadata-Version: 2.1
Name: sphinx-multiproject
Version: 1.0.0
Summary: Build multiple Sphinx projects from a single repository on Read the Docs
Home-page: https://sphinx-multiproject.readthedocs.io/
Author: Read the Docs, Inc
Author-email: support@readthedocs.org
Project-URL: Source, https://github.com/readthedocs/sphinx-multiproject/
Project-URL: Bug Tracker, https://github.com/readthedocs/sphinx-multiproject/issues
Classifier: Programming Language :: Python :: 3
Classifier: License :: OSI Approved :: MIT License
Classifier: Operating System :: OS Independent
Classifier: Framework :: Sphinx
Classifier: Framework :: Sphinx :: Extension
Classifier: Topic :: Documentation :: Sphinx
Classifier: Topic :: Software Development :: Documentation
Requires-Python: >=3.7
License-File: LICENSE
